nagatoai_core/agent/agent.py
nagatoai_core/agent/anthropic.py
nagatoai_core/agent/deepseek.py
nagatoai_core/agent/factory.py
nagatoai_core/agent/google.py
nagatoai_core/agent/groq.py
nagatoai_core/agent/message.py
nagatoai_core/agent/openai.py
nagatoai_core/chain/accumulator_link.py
nagatoai_core/chain/adapter_link.py
nagatoai_core/chain/agent_link.py
nagatoai_core/chain/agent_param_converter.py
nagatoai_core/chain/chain.py
nagatoai_core/chain/ring.py
nagatoai_core/chain/tool_link.py
nagatoai_core/common/common.py
nagatoai_core/common/structured_logger.py
nagatoai_core/graph/abstract_flow.py
nagatoai_core/graph/abstract_node.py
nagatoai_core/graph/agent_node.py
nagatoai_core/graph/conditional_flow.py
nagatoai_core/graph/graph.py
nagatoai_core/graph/parallel_flow.py
nagatoai_core/graph/sequential_flow.py
nagatoai_core/graph/tool_node.py
nagatoai_core/graph/tool_node_with_params_conversion.py
nagatoai_core/graph/transformer_flow.py
nagatoai_core/graph/types.py
nagatoai_core/graph/unfold_flow.py
nagatoai_core/memory/tool_run_cache.py
nagatoai_core/mission/mission.py
nagatoai_core/mission/task.py
nagatoai_core/prompt/template/prompt_template.py
nagatoai_core/prompt/templates.py
nagatoai_core/runner/single_agent_task_runner.py
nagatoai_core/runner/single_critic_evaluator.py
nagatoai_core/runner/task_evaluator.py
nagatoai_core/runner/task_runner.py
nagatoai_core/tool/abstract_tool.py
nagatoai_core/tool/common/audio/audio_segment_with_timestamps.py
nagatoai_core/tool/common/audio/utils.py
nagatoai_core/tool/lib/audio/afplay.py
nagatoai_core/tool/lib/audio/stt/assemblyai.py
nagatoai_core/tool/lib/audio/stt/groq_whisper.py
nagatoai_core/tool/lib/audio/stt/openai_whisper.py
nagatoai_core/tool/lib/audio/tts/eleven_labs.py
nagatoai_core/tool/lib/audio/tts/openai.py
nagatoai_core/tool/lib/audio/video_to_mp3.py
nagatoai_core/tool/lib/filesystem/csv_reader.py
nagatoai_core/tool/lib/filesystem/file_checker.py
nagatoai_core/tool/lib/filesystem/text_file_reader.py
nagatoai_core-0.25.0.dist-info/LICENSE
nagatoai_core-0.25.0.dist-info/METADATA
nagatoai_core-0.25.0.dist-info/WHEEL
nagatoai_core-0.25.0.dist-info/RECORD
