Metadata-Version: 2.1
Name: nagatoai_core
Version: 0.25.0
Summary: Nagato-AI is an intuitive AI Agent library that works across multiple LLMs
Author: Eddie Forson
Author-email: eddie@edforson.me
Requires-Python: >=3.12,<4.0
Classifier: Programming Language :: Python :: 3
Classifier: Programming Language :: Python :: 3.12
Requires-Dist: anthropic (>=0.23.1,<0.24.0)
Requires-Dist: assemblyai (>=0.28.0,<0.29.0)
Requires-Dist: beautifulsoup4 (>=4.12.3,<5.0.0)
Requires-Dist: chardet (>=5.2.0,<6.0.0)
Requires-Dist: ffmpeg-python (>=0.2.0,<0.3.0)
Requires-Dist: google-genai (>=1.1.0,<2.0.0)
Requires-Dist: groq (>=0.5.0,<0.6.0)
Requires-Dist: langfuse (>=2.40.0,<3.0.0)
Requires-Dist: lxml (>=5.1.0,<6.0.0)
Requires-Dist: openai (>=1.14.3,<2.0.0)
Requires-Dist: protobuf (>=5.29.3,<6.0.0)
Requires-Dist: pydantic (>=2.6.4,<3.0.0)
Requires-Dist: pydantic-settings (>=2.2.1,<3.0.0)
Requires-Dist: pydub (>=0.25.1,<0.26.0)
Requires-Dist: pytest (>=8.1.1,<9.0.0)
Requires-Dist: python-dateutil (>=2.9.0.post0,<3.0.0)
Requires-Dist: python-dotenv (>=1.0.1,<2.0.0)
Requires-Dist: python-levenshtein (>=0.25.1,<0.26.0)
Requires-Dist: pytube (>=15.0.0,<16.0.0)
Requires-Dist: pytubefix (>=8.6.0,<9.0.0)
Requires-Dist: requests (>=2.31.0,<3.0.0)
Requires-Dist: rich (>=13.7.1,<14.0.0)
Requires-Dist: scrapingbee (>=2.0.1,<3.0.0)
Requires-Dist: structlog (>=25.1.0,<26.0.0)
